dj_pony/pendulumfield/__init__.py
dj_pony/pendulumfield/apps.py
dj_pony/pendulumfield/fields.py
dj_pony/pendulumfield/forms.py
dj_pony.pendulumfield-0.1.0.dist-info/LICENSE
dj_pony.pendulumfield-0.1.0.dist-info/WHEEL
dj_pony.pendulumfield-0.1.0.dist-info/METADATA
dj_pony.pendulumfield-0.1.0.dist-info/RECORD
