Metadata-Version: 2.1
Name: dj-pony.pendulumfield
Version: 0.1.0
Summary: A PendulumField for Django that does all the work for you.
Author: Samuel Bishop
Author-email: sam@techdragon.io
Requires-Python: >=3.6,<4.0
Classifier: Programming Language :: Python :: 3
Classifier: Programming Language :: Python :: 3.6
Classifier: Programming Language :: Python :: 3.7
Requires-Dist: django (>=2.2)
Requires-Dist: pendulum (>=2.1.2,<3.0.0)
